hydromt/__init__.py
hydromt/_abstract_base.py
hydromt/_compat.py
hydromt/config.py
hydromt/error.py
hydromt/plugins.py
hydromt/readers.py
hydromt/writers.py
hydromt/_utils/__init__.py
hydromt/_utils/caching.py
hydromt/_utils/dataset.py
hydromt/_utils/deep_merge.py
hydromt/_utils/dictionaries.py
hydromt/_utils/elevation.py
hydromt/_utils/log.py
hydromt/_utils/naming_convention.py
hydromt/_utils/nodata.py
hydromt/_utils/path.py
hydromt/_utils/rgetattr.py
hydromt/_utils/steps_validator.py
hydromt/_utils/temp_env.py
hydromt/_utils/unused_kwargs.py
hydromt/_utils/uris.py
hydromt/_validators/__init__.py
hydromt/_validators/data_catalog_v0x.py
hydromt/_validators/data_catalog_v1x.py
hydromt/_validators/model_config.py
hydromt/_validators/region.py
hydromt/cli/__init__.py
hydromt/cli/_utils.py
hydromt/cli/main.py
hydromt/data_catalog/__init__.py
hydromt/data_catalog/data_catalog.py
hydromt/data_catalog/predefined_catalog.py
hydromt/data_catalog/adapters/__init__.py
hydromt/data_catalog/adapters/adapter_utils.py
hydromt/data_catalog/adapters/data_adapter_base.py
hydromt/data_catalog/adapters/dataframe.py
hydromt/data_catalog/adapters/dataset.py
hydromt/data_catalog/adapters/geodataframe.py
hydromt/data_catalog/adapters/geodataset.py
hydromt/data_catalog/adapters/rasterdataset.py
hydromt/data_catalog/drivers/__init__.py
hydromt/data_catalog/drivers/base_driver.py
hydromt/data_catalog/drivers/preprocessing.py
hydromt/data_catalog/drivers/dataframe/__init__.py
hydromt/data_catalog/drivers/dataframe/dataframe_driver.py
hydromt/data_catalog/drivers/dataframe/pandas_driver.py
hydromt/data_catalog/drivers/dataset/__init__.py
hydromt/data_catalog/drivers/dataset/dataset_driver.py
hydromt/data_catalog/drivers/dataset/xarray_driver.py
hydromt/data_catalog/drivers/geodataframe/__init__.py
hydromt/data_catalog/drivers/geodataframe/geodataframe_driver.py
hydromt/data_catalog/drivers/geodataframe/pyogrio_driver.py
hydromt/data_catalog/drivers/geodataframe/table_driver.py
hydromt-1.3.0.dist-info/entry_points.txt
hydromt-1.3.0.dist-info/licenses/LICENSE
hydromt-1.3.0.dist-info/WHEEL
hydromt-1.3.0.dist-info/METADATA
hydromt-1.3.0.dist-info/RECORD
