Metadata-Version: 2.4
Name: hydromt
Version: 1.3.0
Summary: HydroMT: Automated and reproducible model building and analysis.
Author-email: Dirk Eilander <dirk.eilander@deltares.nl>, Hélène Boisgontier <helene.boisgontier@deltares.nl>, Sam Vente <sam.vente@deltares.nl>
Requires-Python: >=3.11
Classifier: Development Status :: 5 - Production/Stable
Classifier: Intended Audience :: Developers
Classifier: Intended Audience :: Science/Research
Classifier: Topic :: Scientific/Engineering :: Hydrology
Classifier: License :: OSI Approved :: MIT License
Classifier: Programming Language :: Python :: 3
Classifier: Programming Language :: Python :: 3.11
Classifier: Programming Language :: Python :: 3.12
Classifier: Programming Language :: Python :: 3.13
License-File: LICENSE
Requires-Dist: affine
Requires-Dist: bottleneck
Requires-Dist: click
Requires-Dist: dask
Requires-Dist: fsspec[http]
Requires-Dist: geopandas[all]>=0.10
Requires-Dist: importlib_metadata
Requires-Dist: mercantile
Requires-Dist: netcdf4
Requires-Dist: numba
Requires-Dist: numpy
Requires-Dist: packaging
Requires-Dist: pandas
Requires-Dist: pooch
Requires-Dist: pyarrow
Requires-Dist: pydantic~=2.4
Requires-Dist: pydantic-settings~=2.2
Requires-Dist: pyflwdir>=0.5.4
Requires-Dist: pyogrio>=0.6
Requires-Dist: pyproj
Requires-Dist: pystac
Requires-Dist: pyyaml
Requires-Dist: rasterio
Requires-Dist: requests
Requires-Dist: rioxarray
Requires-Dist: scipy
Requires-Dist: shapely>=2.1.0
Requires-Dist: tomli
Requires-Dist: tomli-w
Requires-Dist: universal_pathlib>=0.2
Requires-Dist: xarray
Requires-Dist: xmltodict
Requires-Dist: xugrid>=0.9.0
Requires-Dist: zarr>=3.1,<4
Requires-Dist: flit ; extra == "dev"
Requires-Dist: mypy ; extra == "dev"
Requires-Dist: pandas-stubs ; extra == "dev"
Requires-Dist: pre-commit ; extra == "dev"
Requires-Dist: ruff ; extra == "dev"
Requires-Dist: twine ; extra == "dev"
Requires-Dist: types-openpyxl ; extra == "dev"
Requires-Dist: types-PyYAML ; extra == "dev"
Requires-Dist: types-Pillow ; extra == "dev"
Requires-Dist: types-requests ; extra == "dev"
Requires-Dist: types-xmltodict ; extra == "dev"
Requires-Dist: hydromt[examples, extra] ; extra == "doc"
Requires-Dist: nbsphinx ; extra == "doc"
Requires-Dist: pydata-sphinx-theme>=0.15.2 ; extra == "doc"
Requires-Dist: sphinx_autosummary_accessors ; extra == "doc"
Requires-Dist: sphinx ; extra == "doc"
Requires-Dist: sphinx_design ; extra == "doc"
Requires-Dist: sphinx-click ; extra == "doc"
Requires-Dist: sbom4python ; extra == "doc"
Requires-Dist: autodoc_pydantic ; extra == "doc"
Requires-Dist: cartopy ; extra == "examples"
Requires-Dist: jupyterlab ; extra == "examples"
Requires-Dist: notebook ; extra == "examples"
Requires-Dist: matplotlib ; extra == "extra"
Requires-Dist: pyet ; extra == "extra"
Requires-Dist: gcsfs>=2023.12.1 ; extra == "io"
Requires-Dist: fastparquet ; extra == "io"
Requires-Dist: openpyxl ; extra == "io"
Requires-Dist: pillow ; extra == "io"
Requires-Dist: s3fs ; extra == "io"
Requires-Dist: hydromt[io, extra, examples] ; extra == "slim"
Requires-Dist: pytest>=8 ; extra == "test"
Requires-Dist: pytest-cov ; extra == "test"
Requires-Dist: pytest-mock ; extra == "test"
Requires-Dist: pytest-timeout ; extra == "test"
Requires-Dist: gdal>=3.5.0 ; extra == "vrt"
Project-URL: Documentation, https://deltares.github.io/hydromt
Project-URL: Source, https://github.com/Deltares/hydromt
Provides-Extra: dev
Provides-Extra: doc
Provides-Extra: examples
Provides-Extra: extra
Provides-Extra: io
Provides-Extra: slim
Provides-Extra: test
Provides-Extra: vrt
